mach/__init__.py
mach/base.py
mach/config.py
mach/decorators.py
mach/dispatcher.py
mach/logging.py
mach/main.py
mach/registrar.py
mach/terminal.py
mach-0.6.dist-info/DESCRIPTION.rst
mach-0.6.dist-info/METADATA
mach-0.6.dist-info/RECORD
mach-0.6.dist-info/WHEEL
mach-0.6.dist-info/metadata.json
mach-0.6.dist-info/top_level.txt
