Metadata-Version: 1.1
Name: mach
Version: 0.6
Summary: Generic command line command dispatching framework.
Home-page: https://developer.mozilla.org/en-US/docs/Developer_Guide/mach
Author: Gregory Szorc
Author-email: gregory.szorc@gmail.com
License: MPL 2.0
Platform: UNKNOWN
Classifier: Environment :: Console
Classifier: Development Status :: 3 - Alpha
Classifier: License :: OSI Approved :: Mozilla Public License 2.0 (MPL 2.0)
Classifier: Natural Language :: English
